{"_type":"export","__export_format":4,"__export_date":"2019-10-22T01:44:58.631Z","__export_source":"insomnia.desktop.app:v7.0.1","resources":[{"_id":"req_f0d6c2174491434ea0392af04f15944a","authentication":{},"body":{"mimeType":"application/json","text":"{\n\t\"email\": \"admin@gympoint.com\",\n\t\"password\": \"123456\"\n}"},"created":1571691233094,"description":"","headers":[{"id":"pair_9c9466db52d64cd6ab45adc4fb232cac","name":"Content-Type","value":"application/json"}],"isPrivate":false,"metaSortKey":-1571691233094,"method":"POST","modified":1571698267677,"name":"Create","parameters":[],"parentId":"fld_0c907870612442cd9bc03eba7ddf2d23","settingDisableRenderRequestBody":false,"settingEncodeUrl":true,"settingRebuildPath":true,"settingSendCookies":true,"settingStoreCookies":true,"url":"{{ base_url  }}/sessions","_type":"request"},{"_id":"fld_0c907870612442cd9bc03eba7ddf2d23","created":1571691211302,"description":"","environment":{},"environmentPropertyOrder":null,"metaSortKey":-1571691211302,"modified":1571691211302,"name":"Session","parentId":"wrk_e8f7b7bb04e14a17a35f2a3ec5106c38","_type":"request_group"},{"_id":"wrk_e8f7b7bb04e14a17a35f2a3ec5106c38","created":1571688829913,"description":"","modified":1571688829913,"name":"GymPoint","parentId":null,"_type":"workspace"},{"_id":"req_8e7edfead8e2473c8ba8df5d1f8667e6","authentication":{"token":"eyJhbGciOiJIUzI1NiIsInR5cCI6IkpXVCJ9.eyJpZCI6MSwiaWF0IjoxNTcxNjkxMzQ1LCJleHAiOjE1NzIyOTYxNDV9.1lsAFZxL7No-_GC4fdK2yYPWr9VWcwr8nK35xFMWdtk","type":"bearer"},"body":{"mimeType":"application/json","text":"{\n\t\"name\": \"Student 1\",\n\t\"email\": \"student1@gympoint.com\",\n\t\"age\": 19,\n\t\"weight\": 78.4,\n\t\"height\": 1.75\n}"},"created":1571688891849,"description":"","headers":[{"id":"pair_7ab29fe5ddf94ce1b2c1eaafd77464e6","name":"Content-Type","value":"application/json"}],"isPrivate":false,"metaSortKey":-1571688891849,"method":"POST","modified":1571697584158,"name":"Create","parameters":[],"parentId":"fld_96ffe92521854fc78b76a174b5856e76","settingDisableRenderRequestBody":false,"settingEncodeUrl":true,"settingRebuildPath":true,"settingSendCookies":true,"settingStoreCookies":true,"url":"{{ base_url  }}/students","_type":"request"},{"_id":"fld_96ffe92521854fc78b76a174b5856e76","created":1571688879490,"description":"","environment":{},"environmentPropertyOrder":null,"metaSortKey":-1571688879490,"modified":1571688879490,"name":"Student","parentId":"wrk_e8f7b7bb04e14a17a35f2a3ec5106c38","_type":"request_group"},{"_id":"req_3abb564eeb424436b06ca78f08918146","authentication":{"token":"eyJhbGciOiJIUzI1NiIsInR5cCI6IkpXVCJ9.eyJpZCI6MSwiaWF0IjoxNTcxNjkxMzQ1LCJleHAiOjE1NzIyOTYxNDV9.1lsAFZxL7No-_GC4fdK2yYPWr9VWcwr8nK35xFMWdtk","type":"bearer"},"body":{"mimeType":"application/json","text":"{\n\t\"studentId\": 1,\n\t\"email\": \"student1@gympoint.com\",\n\t\"name\": \"Student 1\",\n\t\"age\": 22,\n\t\"weight\": 68.9,\n\t\"height\": 1.78\n}"},"created":1571691473970,"description":"","headers":[{"id":"pair_7ab29fe5ddf94ce1b2c1eaafd77464e6","name":"Content-Type","value":"application/json"}],"isPrivate":false,"metaSortKey":-1571641192374.5,"method":"PUT","modified":1571697683552,"name":"Update","parameters":[],"parentId":"fld_96ffe92521854fc78b76a174b5856e76","settingDisableRenderRequestBody":false,"settingEncodeUrl":true,"settingRebuildPath":true,"settingSendCookies":true,"settingStoreCookies":true,"url":"{{ base_url  }}/students","_type":"request"},{"_id":"env_c0a44a7223d656413bba9c8102b088a4e8b6ff2d","color":null,"created":1571688830090,"data":{"base_url":"http://localhost:3333"},"dataPropertyOrder":{"&":["base_url"]},"isPrivate":false,"metaSortKey":1571688830090,"modified":1571688857913,"name":"Base Environment","parentId":"wrk_e8f7b7bb04e14a17a35f2a3ec5106c38","_type":"environment"},{"_id":"jar_c0a44a7223d656413bba9c8102b088a4e8b6ff2d","cookies":[],"created":1571688830095,"modified":1571688830095,"name":"Default Jar","parentId":"wrk_e8f7b7bb04e14a17a35f2a3ec5106c38","_type":"cookie_jar"}]}